{
  "round": 25,
  "nodes": {
    "0": {
      "accuracy": 0.8956999778747559,
      "test_loss": 0.3554590344429016,
      "precision": 1.0,
      "recall": 0.0,
      "f1_score": 0.0,
      "update_norm": 0.04695267230272293,
      "is_attacker": false
    },
    "1": {
      "accuracy": 0.8947999477386475,
      "test_loss": 0.35898110270500183,
      "precision": 1.0,
      "recall": 0.0,
      "f1_score": 0.0,
      "update_norm": 0.04846121370792389,
      "is_attacker": false
    },
    "2": {
      "accuracy": 0.9000999927520752,
      "test_loss": 0.35097119212150574,
      "precision": 1.0,
      "recall": 0.0,
      "f1_score": 0.0,
      "update_norm": 0.05516832321882248,
      "is_attacker": false
    },
    "3": {
      "accuracy": 0.8944999575614929,
      "test_loss": 0.3612290918827057,
      "precision": 1.0,
      "recall": 0.0,
      "f1_score": 0.0,
      "update_norm": 0.05315166711807251,
      "is_attacker": false
    },
    "4": {
      "accuracy": 0.8930999636650085,
      "test_loss": 0.3702111840248108,
      "precision": 1.0,
      "recall": 0.0,
      "f1_score": 0.0,
      "update_norm": 0.04638007655739784,
      "is_attacker": false
    },
    "5": {
      "accuracy": 0.8938999772071838,
      "test_loss": 0.36454129219055176,
      "precision": 1.0,
      "recall": 0.0,
      "f1_score": 0.0,
      "update_norm": 0.04913166165351868,
      "is_attacker": false
    },
    "6": {
      "accuracy": 0.8976999521255493,
      "test_loss": 0.36280500888824463,
      "precision": 1.0,
      "recall": 0.0,
      "f1_score": 0.0,
      "update_norm": 0.046396978199481964,
      "is_attacker": false
    },
    "7": {
      "accuracy": 0.9014999866485596,
      "test_loss": 0.3504776358604431,
      "precision": 1.0,
      "recall": 0.0,
      "f1_score": 0.0,
      "update_norm": 0.05067209526896477,
      "is_attacker": false
    },
    "8": {
      "accuracy": 0.8995999693870544,
      "test_loss": 0.3524300158023834,
      "precision": 1.0,
      "recall": 0.0,
      "f1_score": 0.0,
      "update_norm": 0.04676692560315132,
      "is_attacker": false
    },
    "9": {
      "accuracy": 0.8977999687194824,
      "test_loss": 0.35592594742774963,
      "precision": 1.0,
      "recall": 0.0,
      "f1_score": 0.0,
      "update_norm": 0.04759363457560539,
      "is_attacker": false
    },
    "10": {
      "accuracy": 0.8926999568939209,
      "test_loss": 0.3689386248588562,
      "precision": 1.0,
      "recall": 0.0,
      "f1_score": 0.0,
      "update_norm": 0.04651545360684395,
      "is_attacker": false
    },
    "11": {
      "accuracy": 0.8933999538421631,
      "test_loss": 0.36374038457870483,
      "precision": 1.0,
      "recall": 0.0,
      "f1_score": 0.0,
      "update_norm": 0.04778938740491867,
      "is_attacker": false
    },
    "12": {
      "accuracy": 0.8913999795913696,
      "test_loss": 0.37123480439186096,
      "precision": 1.0,
      "recall": 0.0,
      "f1_score": 0.0,
      "update_norm": 0.04741078242659569,
      "is_attacker": false
    },
    "13": {
      "accuracy": 0.8931999802589417,
      "test_loss": 0.36660394072532654,
      "precision": 1.0,
      "recall": 0.0,
      "f1_score": 0.0,
      "update_norm": 0.046777330338954926,
      "is_attacker": false
    },
    "14": {
      "accuracy": 0.8981999754905701,
      "test_loss": 0.36534029245376587,
      "precision": 1.0,
      "recall": 0.0,
      "f1_score": 0.0,
      "update_norm": 0.047295235097408295,
      "is_attacker": false
    },
    "15": {
      "accuracy": 0.8950999975204468,
      "test_loss": 0.3714160919189453,
      "precision": 1.0,
      "recall": 0.0,
      "f1_score": 0.0,
      "update_norm": 0.04788066819310188,
      "is_attacker": false
    },
    "16": {
      "accuracy": 0.8956999778747559,
      "test_loss": 0.3618243932723999,
      "precision": 1.0,
      "recall": 0.0,
      "f1_score": 0.0,
      "update_norm": 0.0484095960855484,
      "is_attacker": false
    },
    "17": {
      "accuracy": 0.8949999809265137,
      "test_loss": 0.36356469988822937,
      "precision": 1.0,
      "recall": 0.0,
      "f1_score": 0.0,
      "update_norm": 0.047123268246650696,
      "is_attacker": false
    },
    "18": {
      "accuracy": 0.8999999761581421,
      "test_loss": 0.3498518168926239,
      "precision": 1.0,
      "recall": 0.0,
      "f1_score": 0.0,
      "update_norm": 0.05123235285282135,
      "is_attacker": false
    },
    "19": {
      "accuracy": 0.8935999870300293,
      "test_loss": 0.35965442657470703,
      "precision": 1.0,
      "recall": 0.0,
      "f1_score": 0.0,
      "update_norm": 0.05166172236204147,
      "is_attacker": false
    },
    "20": {
      "accuracy": 0.8985999822616577,
      "test_loss": 0.358455628156662,
      "precision": 1.0,
      "recall": 0.0,
      "f1_score": 0.0,
      "update_norm": 0.048341646790504456,
      "is_attacker": false
    },
    "21": {
      "accuracy": 0.895799994468689,
      "test_loss": 0.3651244342327118,
      "precision": 1.0,
      "recall": 0.0,
      "f1_score": 0.0,
      "update_norm": 0.05064135417342186,
      "is_attacker": false
    },
    "22": {
      "accuracy": 0.8948999643325806,
      "test_loss": 0.3682149350643158,
      "precision": 1.0,
      "recall": 0.0,
      "f1_score": 0.0,
      "update_norm": 0.04958084598183632,
      "is_attacker": false
    },
    "23": {
      "accuracy": 0.8933999538421631,
      "test_loss": 0.36141014099121094,
      "precision": 1.0,
      "recall": 0.0,
      "f1_score": 0.0,
      "update_norm": 0.05065344274044037,
      "is_attacker": false
    },
    "24": {
      "accuracy": 0.8981999754905701,
      "test_loss": 0.3592599332332611,
      "precision": 1.0,
      "recall": 0.0,
      "f1_score": 0.0,
      "update_norm": 0.047129351645708084,
      "is_attacker": false
    },
    "25": {
      "accuracy": 0.8981999754905701,
      "test_loss": 0.35567474365234375,
      "precision": 1.0,
      "recall": 0.0,
      "f1_score": 0.0,
      "update_norm": 0.04970528930425644,
      "is_attacker": false
    },
    "26": {
      "accuracy": 0.8986999988555908,
      "test_loss": 0.3510534465312958,
      "precision": 1.0,
      "recall": 0.0,
      "f1_score": 0.0,
      "update_norm": 0.0497344508767128,
      "is_attacker": false
    },
    "27": {
      "accuracy": 0.8989999890327454,
      "test_loss": 0.35153093934059143,
      "precision": 1.0,
      "recall": 0.0,
      "f1_score": 0.0,
      "update_norm": 0.05033271387219429,
      "is_attacker": false
    },
    "28": {
      "accuracy": 0.8955000042915344,
      "test_loss": 0.3549385666847229,
      "precision": 1.0,
      "recall": 0.0,
      "f1_score": 0.0,
      "update_norm": 0.048579294234514236,
      "is_attacker": false
    },
    "29": {
      "accuracy": 0.899399995803833,
      "test_loss": 0.35738644003868103,
      "precision": 1.0,
      "recall": 0.0,
      "f1_score": 0.0,
      "update_norm": 0.04727175831794739,
      "is_attacker": false
    },
    "30": {
      "accuracy": 0.8974999785423279,
      "test_loss": 0.3550337553024292,
      "precision": 1.0,
      "recall": 0.0,
      "f1_score": 0.0,
      "update_norm": 0.052063386887311935,
      "is_attacker": false
    },
    "31": {
      "accuracy": 0.8947999477386475,
      "test_loss": 0.3677908182144165,
      "precision": 1.0,
      "recall": 0.0,
      "f1_score": 0.0,
      "update_norm": 0.04945295304059982,
      "is_attacker": false
    },
    "32": {
      "accuracy": 0.9012999534606934,
      "test_loss": 0.34632787108421326,
      "precision": 1.0,
      "recall": 0.0,
      "f1_score": 0.0,
      "update_norm": 0.04763655737042427,
      "is_attacker": false
    },
    "33": {
      "accuracy": 0.8973000049591064,
      "test_loss": 0.3568148910999298,
      "precision": 1.0,
      "recall": 0.0,
      "f1_score": 0.0,
      "update_norm": 0.050262000411748886,
      "is_attacker": false
    },
    "34": {
      "accuracy": 0.8960999846458435,
      "test_loss": 0.369860976934433,
      "precision": 1.0,
      "recall": 0.0,
      "f1_score": 0.0,
      "update_norm": 0.04671019688248634,
      "is_attacker": false
    },
    "35": {
      "accuracy": 0.8949999809265137,
      "test_loss": 0.36351990699768066,
      "precision": 1.0,
      "recall": 0.0,
      "f1_score": 0.0,
      "update_norm": 0.04774677753448486,
      "is_attacker": false
    },
    "36": {
      "accuracy": 0.8922999501228333,
      "test_loss": 0.3667673170566559,
      "precision": 1.0,
      "recall": 0.0,
      "f1_score": 0.0,
      "update_norm": 0.05119327828288078,
      "is_attacker": false
    },
    "37": {
      "accuracy": 0.8896999955177307,
      "test_loss": 0.36643916368484497,
      "precision": 1.0,
      "recall": 0.0,
      "f1_score": 0.0,
      "update_norm": 0.05143643543124199,
      "is_attacker": false
    },
    "38": {
      "accuracy": 0.8987999558448792,
      "test_loss": 0.35153594613075256,
      "precision": 1.0,
      "recall": 0.0,
      "f1_score": 0.0,
      "update_norm": 0.05252653732895851,
      "is_attacker": false
    },
    "39": {
      "accuracy": 0.8977999687194824,
      "test_loss": 0.3507908582687378,
      "precision": 1.0,
      "recall": 0.0,
      "f1_score": 0.0,
      "update_norm": 0.05167173966765404,
      "is_attacker": false
    },
    "40": {
      "accuracy": 0.8955000042915344,
      "test_loss": 0.35682621598243713,
      "precision": 1.0,
      "recall": 0.0,
      "f1_score": 0.0,
      "update_norm": 0.0476439967751503,
      "is_attacker": false
    },
    "41": {
      "accuracy": 0.8899999856948853,
      "test_loss": 0.3714483082294464,
      "precision": 1.0,
      "recall": 0.0,
      "f1_score": 0.0,
      "update_norm": 0.0477917343378067,
      "is_attacker": false
    },
    "42": {
      "accuracy": 0.9005999565124512,
      "test_loss": 0.35326680541038513,
      "precision": 1.0,
      "recall": 0.0,
      "f1_score": 0.0,
      "update_norm": 0.05030388757586479,
      "is_attacker": false
    },
    "43": {
      "accuracy": 0.8912000060081482,
      "test_loss": 0.37046322226524353,
      "precision": 1.0,
      "recall": 0.0,
      "f1_score": 0.0,
      "update_norm": 0.04680066555738449,
      "is_attacker": false
    },
    "44": {
      "accuracy": 0.8947999477386475,
      "test_loss": 0.36107122898101807,
      "precision": 1.0,
      "recall": 0.0,
      "f1_score": 0.0,
      "update_norm": 0.04972602799534798,
      "is_attacker": false
    },
    "45": {
      "accuracy": 0.8984999656677246,
      "test_loss": 0.35555949807167053,
      "precision": 1.0,
      "recall": 0.0,
      "f1_score": 0.0,
      "update_norm": 0.04954807832837105,
      "is_attacker": false
    },
    "46": {
      "accuracy": 0.8947999477386475,
      "test_loss": 0.36066770553588867,
      "precision": 1.0,
      "recall": 0.0,
      "f1_score": 0.0,
      "update_norm": 0.05039685219526291,
      "is_attacker": false
    },
    "47": {
      "accuracy": 0.8992999792098999,
      "test_loss": 0.35033178329467773,
      "precision": 1.0,
      "recall": 0.0,
      "f1_score": 0.0,
      "update_norm": 0.05056030675768852,
      "is_attacker": false
    },
    "48": {
      "accuracy": 0.8978999853134155,
      "test_loss": 0.3614523708820343,
      "precision": 1.0,
      "recall": 0.0,
      "f1_score": 0.0,
      "update_norm": 0.05012679845094681,
      "is_attacker": false
    },
    "49": {
      "accuracy": 0.8928999900817871,
      "test_loss": 0.3649928569793701,
      "precision": 1.0,
      "recall": 0.0,
      "f1_score": 0.0,
      "update_norm": 0.04858670011162758,
      "is_attacker": false
    },
    "50": {
      "accuracy": 0.8973000049591064,
      "test_loss": 0.3526346981525421,
      "precision": 1.0,
      "recall": 0.0,
      "f1_score": 0.0,
      "update_norm": 0.04706629738211632,
      "is_attacker": false
    },
    "51": {
      "accuracy": 0.8937000036239624,
      "test_loss": 0.3656477928161621,
      "precision": 1.0,
      "recall": 0.0,
      "f1_score": 0.0,
      "update_norm": 0.04757675901055336,
      "is_attacker": false
    },
    "52": {
      "accuracy": 0.8974999785423279,
      "test_loss": 0.3626382350921631,
      "precision": 1.0,
      "recall": 0.0,
      "f1_score": 0.0,
      "update_norm": 0.048409368842840195,
      "is_attacker": false
    },
    "53": {
      "accuracy": 0.8937999606132507,
      "test_loss": 0.36451998353004456,
      "precision": 1.0,
      "recall": 0.0,
      "f1_score": 0.0,
      "update_norm": 0.04846614599227905,
      "is_attacker": false
    },
    "54": {
      "accuracy": 0.8938999772071838,
      "test_loss": 0.3626428246498108,
      "precision": 1.0,
      "recall": 0.0,
      "f1_score": 0.0,
      "update_norm": 0.050873760133981705,
      "is_attacker": false
    },
    "55": {
      "accuracy": 0.8962999582290649,
      "test_loss": 0.3670762777328491,
      "precision": 1.0,
      "recall": 0.0,
      "f1_score": 0.0,
      "update_norm": 0.050397466868162155,
      "is_attacker": false
    },
    "56": {
      "accuracy": 0.8912000060081482,
      "test_loss": 0.36274394392967224,
      "precision": 1.0,
      "recall": 0.0,
      "f1_score": 0.0,
      "update_norm": 0.046454329043626785,
      "is_attacker": false
    },
    "57": {
      "accuracy": 0.8941999673843384,
      "test_loss": 0.36186498403549194,
      "precision": 1.0,
      "recall": 0.0,
      "f1_score": 0.0,
      "update_norm": 0.04698225483298302,
      "is_attacker": false
    },
    "58": {
      "accuracy": 0.8966999650001526,
      "test_loss": 0.3623098134994507,
      "precision": 1.0,
      "recall": 0.0,
      "f1_score": 0.0,
      "update_norm": 0.04975632205605507,
      "is_attacker": false
    },
    "59": {
      "accuracy": 0.9010999798774719,
      "test_loss": 0.3554885685443878,
      "precision": 1.0,
      "recall": 0.0,
      "f1_score": 0.0,
      "update_norm": 0.05025283247232437,
      "is_attacker": false
    },
    "60": {
      "accuracy": 0.895799994468689,
      "test_loss": 0.36524075269699097,
      "precision": 1.0,
      "recall": 0.0,
      "f1_score": 0.0,
      "update_norm": 0.04990232363343239,
      "is_attacker": false
    },
    "61": {
      "accuracy": 0.8949999809265137,
      "test_loss": 0.36664292216300964,
      "precision": 1.0,
      "recall": 0.0,
      "f1_score": 0.0,
      "update_norm": 0.047995515167713165,
      "is_attacker": false
    },
    "62": {
      "accuracy": 0.8948999643325806,
      "test_loss": 0.36256322264671326,
      "precision": 1.0,
      "recall": 0.0,
      "f1_score": 0.0,
      "update_norm": 0.050181664526462555,
      "is_attacker": false
    },
    "63": {
      "accuracy": 0.8962000012397766,
      "test_loss": 0.3676607608795166,
      "precision": 1.0,
      "recall": 0.0,
      "f1_score": 0.0,
      "update_norm": 0.04785865545272827,
      "is_attacker": false
    },
    "64": {
      "accuracy": 0.8925999999046326,
      "test_loss": 0.36568281054496765,
      "precision": 1.0,
      "recall": 0.0,
      "f1_score": 0.0,
      "update_norm": 0.05122165381908417,
      "is_attacker": false
    },
    "65": {
      "accuracy": 0.8937000036239624,
      "test_loss": 0.36841410398483276,
      "precision": 1.0,
      "recall": 0.0,
      "f1_score": 0.0,
      "update_norm": 0.052381083369255066,
      "is_attacker": false
    },
    "66": {
      "accuracy": 0.8939999938011169,
      "test_loss": 0.35765931010246277,
      "precision": 1.0,
      "recall": 0.0,
      "f1_score": 0.0,
      "update_norm": 0.049795906990766525,
      "is_attacker": false
    },
    "67": {
      "accuracy": 0.8930999636650085,
      "test_loss": 0.3630813658237457,
      "precision": 1.0,
      "recall": 0.0,
      "f1_score": 0.0,
      "update_norm": 0.05648409202694893,
      "is_attacker": false
    },
    "68": {
      "accuracy": 0.8950999975204468,
      "test_loss": 0.35888513922691345,
      "precision": 1.0,
      "recall": 0.0,
      "f1_score": 0.0,
      "update_norm": 0.05128941312432289,
      "is_attacker": false
    },
    "69": {
      "accuracy": 0.8935999870300293,
      "test_loss": 0.35927096009254456,
      "precision": 1.0,
      "recall": 0.0,
      "f1_score": 0.0,
      "update_norm": 0.0505412258207798,
      "is_attacker": false
    },
    "70": {
      "accuracy": 0.8973999619483948,
      "test_loss": 0.3559972941875458,
      "precision": 1.0,
      "recall": 0.0,
      "f1_score": 0.0,
      "update_norm": 0.04804891720414162,
      "is_attacker": false
    },
    "71": {
      "accuracy": 0.8951999545097351,
      "test_loss": 0.3661860227584839,
      "precision": 1.0,
      "recall": 0.0,
      "f1_score": 0.0,
      "update_norm": 0.04937266558408737,
      "is_attacker": false
    },
    "72": {
      "accuracy": 0.8924999833106995,
      "test_loss": 0.37153303623199463,
      "precision": 1.0,
      "recall": 0.0,
      "f1_score": 0.0,
      "update_norm": 0.04781649261713028,
      "is_attacker": false
    },
    "73": {
      "accuracy": 0.8960999846458435,
      "test_loss": 0.3613000512123108,
      "precision": 1.0,
      "recall": 0.0,
      "f1_score": 0.0,
      "update_norm": 0.0523604154586792,
      "is_attacker": false
    },
    "74": {
      "accuracy": 0.8978999853134155,
      "test_loss": 0.3601037859916687,
      "precision": 1.0,
      "recall": 0.0,
      "f1_score": 0.0,
      "update_norm": 0.0522439181804657,
      "is_attacker": false
    },
    "75": {
      "accuracy": 0.8958999514579773,
      "test_loss": 0.35397467017173767,
      "precision": 1.0,
      "recall": 0.0,
      "f1_score": 0.0,
      "update_norm": 0.05040031671524048,
      "is_attacker": false
    },
    "76": {
      "accuracy": 0.895799994468689,
      "test_loss": 0.3562634289264679,
      "precision": 1.0,
      "recall": 0.0,
      "f1_score": 0.0,
      "update_norm": 0.04893827438354492,
      "is_attacker": false
    },
    "77": {
      "accuracy": 0.8952999711036682,
      "test_loss": 0.3604136109352112,
      "precision": 1.0,
      "recall": 0.0,
      "f1_score": 0.0,
      "update_norm": 0.04841575026512146,
      "is_attacker": false
    },
    "78": {
      "accuracy": 0.8969999551773071,
      "test_loss": 0.35688623785972595,
      "precision": 1.0,
      "recall": 0.0,
      "f1_score": 0.0,
      "update_norm": 0.049989473074674606,
      "is_attacker": false
    },
    "79": {
      "accuracy": 0.8987999558448792,
      "test_loss": 0.350527822971344,
      "precision": 1.0,
      "recall": 0.0,
      "f1_score": 0.0,
      "update_norm": 0.04951076582074165,
      "is_attacker": false
    },
    "80": {
      "accuracy": 0.8942999839782715,
      "test_loss": 0.3579278588294983,
      "precision": 1.0,
      "recall": 0.0,
      "f1_score": 0.0,
      "update_norm": 0.049112796783447266,
      "is_attacker": false
    },
    "81": {
      "accuracy": 0.8973999619483948,
      "test_loss": 0.3502197265625,
      "precision": 1.0,
      "recall": 0.0,
      "f1_score": 0.0,
      "update_norm": 0.05412593111395836,
      "is_attacker": false
    },
    "82": {
      "accuracy": 0.8915999531745911,
      "test_loss": 0.36694052815437317,
      "precision": 1.0,
      "recall": 0.0,
      "f1_score": 0.0,
      "update_norm": 0.050486866384744644,
      "is_attacker": false
    },
    "83": {
      "accuracy": 0.8988999724388123,
      "test_loss": 0.35452190041542053,
      "precision": 1.0,
      "recall": 0.0,
      "f1_score": 0.0,
      "update_norm": 0.048814356327056885,
      "is_attacker": false
    },
    "84": {
      "accuracy": 0.894599974155426,
      "test_loss": 0.3610092103481293,
      "precision": 1.0,
      "recall": 0.0,
      "f1_score": 0.0,
      "update_norm": 0.0467163622379303,
      "is_attacker": false
    },
    "85": {
      "accuracy": 0.897599995136261,
      "test_loss": 0.3576059639453888,
      "precision": 1.0,
      "recall": 0.0,
      "f1_score": 0.0,
      "update_norm": 0.052187319844961166,
      "is_attacker": false
    },
    "86": {
      "accuracy": 0.8976999521255493,
      "test_loss": 0.36211714148521423,
      "precision": 1.0,
      "recall": 0.0,
      "f1_score": 0.0,
      "update_norm": 0.048893798142671585,
      "is_attacker": false
    },
    "87": {
      "accuracy": 0.8935999870300293,
      "test_loss": 0.3606763780117035,
      "precision": 1.0,
      "recall": 0.0,
      "f1_score": 0.0,
      "update_norm": 0.048137106001377106,
      "is_attacker": false
    },
    "88": {
      "accuracy": 0.8977999687194824,
      "test_loss": 0.3581935465335846,
      "precision": 1.0,
      "recall": 0.0,
      "f1_score": 0.0,
      "update_norm": 0.04701843857765198,
      "is_attacker": false
    },
    "89": {
      "accuracy": 0.8974999785423279,
      "test_loss": 0.3588804006576538,
      "precision": 1.0,
      "recall": 0.0,
      "f1_score": 0.0,
      "update_norm": 0.04641790688037872,
      "is_attacker": false
    },
    "90": {
      "accuracy": 0.8964999914169312,
      "test_loss": 0.35985690355300903,
      "precision": 1.0,
      "recall": 0.0,
      "f1_score": 0.0,
      "update_norm": 0.04799003526568413,
      "is_attacker": false
    },
    "91": {
      "accuracy": 0.8951999545097351,
      "test_loss": 0.3645755648612976,
      "precision": 1.0,
      "recall": 0.0,
      "f1_score": 0.0,
      "update_norm": 0.049585580825805664,
      "is_attacker": false
    },
    "92": {
      "accuracy": 0.8985999822616577,
      "test_loss": 0.3492317497730255,
      "precision": 1.0,
      "recall": 0.0,
      "f1_score": 0.0,
      "update_norm": 0.05304189771413803,
      "is_attacker": false
    },
    "93": {
      "accuracy": 0.8932999968528748,
      "test_loss": 0.3638157248497009,
      "precision": 1.0,
      "recall": 0.0,
      "f1_score": 0.0,
      "update_norm": 0.04889388009905815,
      "is_attacker": false
    },
    "94": {
      "accuracy": 0.8942999839782715,
      "test_loss": 0.3623361885547638,
      "precision": 1.0,
      "recall": 0.0,
      "f1_score": 0.0,
      "update_norm": 0.04754721745848656,
      "is_attacker": false
    },
    "95": {
      "accuracy": 0.8955000042915344,
      "test_loss": 0.36168211698532104,
      "precision": 1.0,
      "recall": 0.0,
      "f1_score": 0.0,
      "update_norm": 0.04887007176876068,
      "is_attacker": false
    },
    "96": {
      "accuracy": 0.8951999545097351,
      "test_loss": 0.3685443103313446,
      "precision": 1.0,
      "recall": 0.0,
      "f1_score": 0.0,
      "update_norm": 0.0465230755507946,
      "is_attacker": false
    },
    "97": {
      "accuracy": 0.8973000049591064,
      "test_loss": 0.36010485887527466,
      "precision": 1.0,
      "recall": 0.0,
      "f1_score": 0.0,
      "update_norm": 0.04751289635896683,
      "is_attacker": false
    },
    "98": {
      "accuracy": 0.8988999724388123,
      "test_loss": 0.3575176000595093,
      "precision": 1.0,
      "recall": 0.0,
      "f1_score": 0.0,
      "update_norm": 0.05205671489238739,
      "is_attacker": false
    },
    "99": {
      "accuracy": 0.8937000036239624,
      "test_loss": 0.36257287859916687,
      "precision": 1.0,
      "recall": 0.0,
      "f1_score": 0.0,
      "update_norm": 0.04890292510390282,
      "is_attacker": false
    },
    "100": {
      "accuracy": 0.8998000025749207,
      "test_loss": 0.3545146882534027,
      "precision": 1.0,
      "recall": 0.0,
      "f1_score": 0.0,
      "update_norm": 0.049681149423122406,
      "is_attacker": false
    },
    "101": {
      "accuracy": 0.8947999477386475,
      "test_loss": 0.3621774911880493,
      "precision": 1.0,
      "recall": 0.0,
      "f1_score": 0.0,
      "update_norm": 0.05175295099616051,
      "is_attacker": false
    },
    "102": {
      "accuracy": 0.8916999697685242,
      "test_loss": 0.3655933439731598,
      "precision": 1.0,
      "recall": 0.0,
      "f1_score": 0.0,
      "update_norm": 0.048525869846343994,
      "is_attacker": false
    },
    "103": {
      "accuracy": 0.8959999680519104,
      "test_loss": 0.3560396134853363,
      "precision": 1.0,
      "recall": 0.0,
      "f1_score": 0.0,
      "update_norm": 0.048417769372463226,
      "is_attacker": false
    },
    "104": {
      "accuracy": 0.8944000005722046,
      "test_loss": 0.3643028140068054,
      "precision": 1.0,
      "recall": 0.0,
      "f1_score": 0.0,
      "update_norm": 0.04749483987689018,
      "is_attacker": false
    },
    "105": {
      "accuracy": 0.8935999870300293,
      "test_loss": 0.3638313412666321,
      "precision": 1.0,
      "recall": 0.0,
      "f1_score": 0.0,
      "update_norm": 0.04820159450173378,
      "is_attacker": false
    },
    "106": {
      "accuracy": 0.8952999711036682,
      "test_loss": 0.35551658272743225,
      "precision": 1.0,
      "recall": 0.0,
      "f1_score": 0.0,
      "update_norm": 0.0481378398835659,
      "is_attacker": false
    },
    "107": {
      "accuracy": 0.8962000012397766,
      "test_loss": 0.35329270362854004,
      "precision": 1.0,
      "recall": 0.0,
      "f1_score": 0.0,
      "update_norm": 0.052131202071905136,
      "is_attacker": false
    },
    "108": {
      "accuracy": 0.8934999704360962,
      "test_loss": 0.36503204703330994,
      "precision": 1.0,
      "recall": 0.0,
      "f1_score": 0.0,
      "update_norm": 0.049993112683296204,
      "is_attacker": false
    },
    "109": {
      "accuracy": 0.9009000062942505,
      "test_loss": 0.3543614447116852,
      "precision": 1.0,
      "recall": 0.0,
      "f1_score": 0.0,
      "update_norm": 0.05097058042883873,
      "is_attacker": false
    },
    "110": {
      "accuracy": 0.8978999853134155,
      "test_loss": 0.3552664816379547,
      "precision": 1.0,
      "recall": 0.0,
      "f1_score": 0.0,
      "update_norm": 0.04833747074007988,
      "is_attacker": false
    },
    "111": {
      "accuracy": 0.9005999565124512,
      "test_loss": 0.3489639163017273,
      "precision": 1.0,
      "recall": 0.0,
      "f1_score": 0.0,
      "update_norm": 0.05240009352564812,
      "is_attacker": false
    },
    "112": {
      "accuracy": 0.8955999612808228,
      "test_loss": 0.3591635525226593,
      "precision": 1.0,
      "recall": 0.0,
      "f1_score": 0.0,
      "update_norm": 0.04759717732667923,
      "is_attacker": false
    },
    "113": {
      "accuracy": 0.8955999612808228,
      "test_loss": 0.3541879951953888,
      "precision": 1.0,
      "recall": 0.0,
      "f1_score": 0.0,
      "update_norm": 0.04885602742433548,
      "is_attacker": false
    },
    "114": {
      "accuracy": 0.8926999568939209,
      "test_loss": 0.36552000045776367,
      "precision": 1.0,
      "recall": 0.0,
      "f1_score": 0.0,
      "update_norm": 0.05334833264350891,
      "is_attacker": false
    },
    "115": {
      "accuracy": 0.8987999558448792,
      "test_loss": 0.34798315167427063,
      "precision": 1.0,
      "recall": 0.0,
      "f1_score": 0.0,
      "update_norm": 0.04923278093338013,
      "is_attacker": false
    },
    "116": {
      "accuracy": 0.8941999673843384,
      "test_loss": 0.3550945818424225,
      "precision": 1.0,
      "recall": 0.0,
      "f1_score": 0.0,
      "update_norm": 0.05010612681508064,
      "is_attacker": false
    },
    "117": {
      "accuracy": 0.896399974822998,
      "test_loss": 0.3525654673576355,
      "precision": 1.0,
      "recall": 0.0,
      "f1_score": 0.0,
      "update_norm": 0.048099588602781296,
      "is_attacker": false
    },
    "118": {
      "accuracy": 0.8946999907493591,
      "test_loss": 0.36349937319755554,
      "precision": 1.0,
      "recall": 0.0,
      "f1_score": 0.0,
      "update_norm": 0.047532033175230026,
      "is_attacker": false
    },
    "119": {
      "accuracy": 0.9002999663352966,
      "test_loss": 0.3544032573699951,
      "precision": 1.0,
      "recall": 0.0,
      "f1_score": 0.0,
      "update_norm": 0.05191066488623619,
      "is_attacker": false
    },
    "120": {
      "accuracy": 0.8964999914169312,
      "test_loss": 0.3501337170600891,
      "precision": 1.0,
      "recall": 0.0,
      "f1_score": 0.0,
      "update_norm": 0.048546236008405685,
      "is_attacker": false
    },
    "121": {
      "accuracy": 0.8958999514579773,
      "test_loss": 0.36159443855285645,
      "precision": 1.0,
      "recall": 0.0,
      "f1_score": 0.0,
      "update_norm": 0.047871727496385574,
      "is_attacker": false
    },
    "122": {
      "accuracy": 0.8949999809265137,
      "test_loss": 0.3572307825088501,
      "precision": 1.0,
      "recall": 0.0,
      "f1_score": 0.0,
      "update_norm": 0.047180209308862686,
      "is_attacker": false
    },
    "123": {
      "accuracy": 0.8944000005722046,
      "test_loss": 0.36403679847717285,
      "precision": 1.0,
      "recall": 0.0,
      "f1_score": 0.0,
      "update_norm": 0.04622257128357887,
      "is_attacker": false
    },
    "124": {
      "accuracy": 0.8947999477386475,
      "test_loss": 0.3589288592338562,
      "precision": 1.0,
      "recall": 0.0,
      "f1_score": 0.0,
      "update_norm": 0.04861566424369812,
      "is_attacker": false
    },
    "125": {
      "accuracy": 0.8912000060081482,
      "test_loss": 0.36190521717071533,
      "precision": 1.0,
      "recall": 0.0,
      "f1_score": 0.0,
      "update_norm": 0.050596728920936584,
      "is_attacker": false
    },
    "126": {
      "accuracy": 0.8964999914169312,
      "test_loss": 0.36262333393096924,
      "precision": 1.0,
      "recall": 0.0,
      "f1_score": 0.0,
      "update_norm": 0.04905550554394722,
      "is_attacker": false
    },
    "127": {
      "accuracy": 0.8940999507904053,
      "test_loss": 0.3619314134120941,
      "precision": 1.0,
      "recall": 0.0,
      "f1_score": 0.0,
      "update_norm": 0.04804416745901108,
      "is_attacker": false
    },
    "128": {
      "accuracy": 0.8970999717712402,
      "test_loss": 0.3598713278770447,
      "precision": 1.0,
      "recall": 0.0,
      "f1_score": 0.0,
      "update_norm": 0.04906037077307701,
      "is_attacker": false
    },
    "129": {
      "accuracy": 0.8951999545097351,
      "test_loss": 0.3635207414627075,
      "precision": 1.0,
      "recall": 0.0,
      "f1_score": 0.0,
      "update_norm": 0.04835885018110275,
      "is_attacker": false
    },
    "130": {
      "accuracy": 0.8992999792098999,
      "test_loss": 0.3486771285533905,
      "precision": 1.0,
      "recall": 0.0,
      "f1_score": 0.0,
      "update_norm": 0.05303332209587097,
      "is_attacker": false
    },
    "131": {
      "accuracy": 0.8984999656677246,
      "test_loss": 0.35485541820526123,
      "precision": 1.0,
      "recall": 0.0,
      "f1_score": 0.0,
      "update_norm": 0.04718749225139618,
      "is_attacker": false
    },
    "132": {
      "accuracy": 0.8934999704360962,
      "test_loss": 0.37221893668174744,
      "precision": 1.0,
      "recall": 0.0,
      "f1_score": 0.0,
      "update_norm": 0.045947328209877014,
      "is_attacker": false
    },
    "133": {
      "accuracy": 0.8994999527931213,
      "test_loss": 0.3535497486591339,
      "precision": 1.0,
      "recall": 0.0,
      "f1_score": 0.0,
      "update_norm": 0.04965634271502495,
      "is_attacker": false
    },
    "134": {
      "accuracy": 0.8988999724388123,
      "test_loss": 0.3657993972301483,
      "precision": 1.0,
      "recall": 0.0,
      "f1_score": 0.0,
      "update_norm": 0.04827838018536568,
      "is_attacker": false
    },
    "135": {
      "accuracy": 0.8930000066757202,
      "test_loss": 0.3651193082332611,
      "precision": 1.0,
      "recall": 0.0,
      "f1_score": 0.0,
      "update_norm": 0.048015713691711426,
      "is_attacker": false
    },
    "136": {
      "accuracy": 0.8915999531745911,
      "test_loss": 0.3656095862388611,
      "precision": 1.0,
      "recall": 0.0,
      "f1_score": 0.0,
      "update_norm": 0.04868854582309723,
      "is_attacker": false
    },
    "137": {
      "accuracy": 0.895799994468689,
      "test_loss": 0.3630106747150421,
      "precision": 1.0,
      "recall": 0.0,
      "f1_score": 0.0,
      "update_norm": 0.049177467823028564,
      "is_attacker": false
    },
    "138": {
      "accuracy": 0.8928999900817871,
      "test_loss": 0.36426618695259094,
      "precision": 1.0,
      "recall": 0.0,
      "f1_score": 0.0,
      "update_norm": 0.048141516745090485,
      "is_attacker": false
    },
    "139": {
      "accuracy": 0.8960999846458435,
      "test_loss": 0.3597848415374756,
      "precision": 1.0,
      "recall": 0.0,
      "f1_score": 0.0,
      "update_norm": 0.04730818793177605,
      "is_attacker": false
    },
    "140": {
      "accuracy": 0.9006999731063843,
      "test_loss": 0.3507080376148224,
      "precision": 1.0,
      "recall": 0.0,
      "f1_score": 0.0,
      "update_norm": 0.04933582991361618,
      "is_attacker": false
    },
    "141": {
      "accuracy": 0.8967999815940857,
      "test_loss": 0.36587274074554443,
      "precision": 1.0,
      "recall": 0.0,
      "f1_score": 0.0,
      "update_norm": 0.049935922026634216,
      "is_attacker": false
    },
    "142": {
      "accuracy": 0.8895999789237976,
      "test_loss": 0.3660014569759369,
      "precision": 1.0,
      "recall": 0.0,
      "f1_score": 0.0,
      "update_norm": 0.050045739859342575,
      "is_attacker": false
    },
    "143": {
      "accuracy": 0.899399995803833,
      "test_loss": 0.3567334711551666,
      "precision": 1.0,
      "recall": 0.0,
      "f1_score": 0.0,
      "update_norm": 0.052796099334955215,
      "is_attacker": false
    },
    "144": {
      "accuracy": 0.8939999938011169,
      "test_loss": 0.3654365837574005,
      "precision": 1.0,
      "recall": 0.0,
      "f1_score": 0.0,
      "update_norm": 0.04494303837418556,
      "is_attacker": false
    },
    "145": {
      "accuracy": 0.8949999809265137,
      "test_loss": 0.3707704544067383,
      "precision": 1.0,
      "recall": 0.0,
      "f1_score": 0.0,
      "update_norm": 0.048256903886795044,
      "is_attacker": false
    },
    "146": {
      "accuracy": 0.8924999833106995,
      "test_loss": 0.3621273338794708,
      "precision": 1.0,
      "recall": 0.0,
      "f1_score": 0.0,
      "update_norm": 0.04839854687452316,
      "is_attacker": false
    },
    "147": {
      "accuracy": 0.8964999914169312,
      "test_loss": 0.35914477705955505,
      "precision": 1.0,
      "recall": 0.0,
      "f1_score": 0.0,
      "update_norm": 0.04910299554467201,
      "is_attacker": false
    },
    "148": {
      "accuracy": 0.8996999859809875,
      "test_loss": 0.360394150018692,
      "precision": 1.0,
      "recall": 0.0,
      "f1_score": 0.0,
      "update_norm": 0.04737928509712219,
      "is_attacker": false
    },
    "149": {
      "accuracy": 0.8939999938011169,
      "test_loss": 0.3616870939731598,
      "precision": 1.0,
      "recall": 0.0,
      "f1_score": 0.0,
      "update_norm": 0.049276165664196014,
      "is_attacker": false
    },
    "150": {
      "accuracy": 0.8968999981880188,
      "test_loss": 0.35891810059547424,
      "precision": 1.0,
      "recall": 0.0,
      "f1_score": 0.0,
      "update_norm": 0.05039901286363602,
      "is_attacker": false
    },
    "151": {
      "accuracy": 0.8970999717712402,
      "test_loss": 0.3607645332813263,
      "precision": 1.0,
      "recall": 0.0,
      "f1_score": 0.0,
      "update_norm": 0.05102583020925522,
      "is_attacker": false
    },
    "152": {
      "accuracy": 0.8978999853134155,
      "test_loss": 0.36073359847068787,
      "precision": 1.0,
      "recall": 0.0,
      "f1_score": 0.0,
      "update_norm": 0.04814579710364342,
      "is_attacker": false
    },
    "153": {
      "accuracy": 0.8941999673843384,
      "test_loss": 0.36245596408843994,
      "precision": 1.0,
      "recall": 0.0,
      "f1_score": 0.0,
      "update_norm": 0.05031191185116768,
      "is_attacker": false
    },
    "154": {
      "accuracy": 0.8974999785423279,
      "test_loss": 0.35507717728614807,
      "precision": 1.0,
      "recall": 0.0,
      "f1_score": 0.0,
      "update_norm": 0.0491647832095623,
      "is_attacker": false
    },
    "155": {
      "accuracy": 0.8967999815940857,
      "test_loss": 0.3581126630306244,
      "precision": 1.0,
      "recall": 0.0,
      "f1_score": 0.0,
      "update_norm": 0.05311354622244835,
      "is_attacker": false
    },
    "156": {
      "accuracy": 0.8970999717712402,
      "test_loss": 0.3627619445323944,
      "precision": 1.0,
      "recall": 0.0,
      "f1_score": 0.0,
      "update_norm": 0.04862406104803085,
      "is_attacker": false
    },
    "157": {
      "accuracy": 0.890999972820282,
      "test_loss": 0.36919721961021423,
      "precision": 1.0,
      "recall": 0.0,
      "f1_score": 0.0,
      "update_norm": 0.04931994155049324,
      "is_attacker": false
    },
    "158": {
      "accuracy": 0.8949999809265137,
      "test_loss": 0.35762885212898254,
      "precision": 1.0,
      "recall": 0.0,
      "f1_score": 0.0,
      "update_norm": 0.048094119876623154,
      "is_attacker": false
    },
    "159": {
      "accuracy": 0.8935999870300293,
      "test_loss": 0.3629976212978363,
      "precision": 1.0,
      "recall": 0.0,
      "f1_score": 0.0,
      "update_norm": 0.04939817264676094,
      "is_attacker": false
    },
    "160": {
      "accuracy": 0.8921999931335449,
      "test_loss": 0.3649783432483673,
      "precision": 1.0,
      "recall": 0.0,
      "f1_score": 0.0,
      "update_norm": 0.04768794775009155,
      "is_attacker": false
    },
    "161": {
      "accuracy": 0.897599995136261,
      "test_loss": 0.3543701469898224,
      "precision": 1.0,
      "recall": 0.0,
      "f1_score": 0.0,
      "update_norm": 0.0472833476960659,
      "is_attacker": false
    },
    "162": {
      "accuracy": 0.894599974155426,
      "test_loss": 0.3593335747718811,
      "precision": 1.0,
      "recall": 0.0,
      "f1_score": 0.0,
      "update_norm": 0.04802112281322479,
      "is_attacker": false
    },
    "163": {
      "accuracy": 0.8944999575614929,
      "test_loss": 0.363656222820282,
      "precision": 1.0,
      "recall": 0.0,
      "f1_score": 0.0,
      "update_norm": 0.05045820027589798,
      "is_attacker": false
    },
    "164": {
      "accuracy": 0.8967999815940857,
      "test_loss": 0.3608636260032654,
      "precision": 1.0,
      "recall": 0.0,
      "f1_score": 0.0,
      "update_norm": 0.05303778126835823,
      "is_attacker": false
    },
    "165": {
      "accuracy": 0.8938999772071838,
      "test_loss": 0.36368948221206665,
      "precision": 1.0,
      "recall": 0.0,
      "f1_score": 0.0,
      "update_norm": 0.048366155475378036,
      "is_attacker": false
    },
    "166": {
      "accuracy": 0.8955000042915344,
      "test_loss": 0.36080312728881836,
      "precision": 1.0,
      "recall": 0.0,
      "f1_score": 0.0,
      "update_norm": 0.04915793240070343,
      "is_attacker": false
    },
    "167": {
      "accuracy": 0.8952999711036682,
      "test_loss": 0.35945338010787964,
      "precision": 1.0,
      "recall": 0.0,
      "f1_score": 0.0,
      "update_norm": 0.05027318373322487,
      "is_attacker": false
    },
    "168": {
      "accuracy": 0.8977999687194824,
      "test_loss": 0.3562465310096741,
      "precision": 1.0,
      "recall": 0.0,
      "f1_score": 0.0,
      "update_norm": 0.05030564218759537,
      "is_attacker": false
    },
    "169": {
      "accuracy": 0.8946999907493591,
      "test_loss": 0.36670368909835815,
      "precision": 1.0,
      "recall": 0.0,
      "f1_score": 0.0,
      "update_norm": 0.047298695892095566,
      "is_attacker": false
    },
    "170": {
      "accuracy": 0.8967999815940857,
      "test_loss": 0.3633875846862793,
      "precision": 1.0,
      "recall": 0.0,
      "f1_score": 0.0,
      "update_norm": 0.05685913562774658,
      "is_attacker": false
    },
    "171": {
      "accuracy": 0.8981999754905701,
      "test_loss": 0.3619115352630615,
      "precision": 1.0,
      "recall": 0.0,
      "f1_score": 0.0,
      "update_norm": 0.04742944613099098,
      "is_attacker": false
    },
    "172": {
      "accuracy": 0.895799994468689,
      "test_loss": 0.36052605509757996,
      "precision": 1.0,
      "recall": 0.0,
      "f1_score": 0.0,
      "update_norm": 0.04745756462216377,
      "is_attacker": false
    },
    "173": {
      "accuracy": 0.8889999985694885,
      "test_loss": 0.3720238208770752,
      "precision": 1.0,
      "recall": 0.0,
      "f1_score": 0.0,
      "update_norm": 0.05163504555821419,
      "is_attacker": false
    },
    "174": {
      "accuracy": 0.8949999809265137,
      "test_loss": 0.36503326892852783,
      "precision": 1.0,
      "recall": 0.0,
      "f1_score": 0.0,
      "update_norm": 0.04899980500340462,
      "is_attacker": false
    },
    "175": {
      "accuracy": 0.8950999975204468,
      "test_loss": 0.3584577739238739,
      "precision": 1.0,
      "recall": 0.0,
      "f1_score": 0.0,
      "update_norm": 0.05327591300010681,
      "is_attacker": false
    },
    "176": {
      "accuracy": 0.9004999995231628,
      "test_loss": 0.3555755019187927,
      "precision": 1.0,
      "recall": 0.0,
      "f1_score": 0.0,
      "update_norm": 0.05183501914143562,
      "is_attacker": false
    },
    "177": {
      "accuracy": 0.8981999754905701,
      "test_loss": 0.3549657166004181,
      "precision": 1.0,
      "recall": 0.0,
      "f1_score": 0.0,
      "update_norm": 0.04659005254507065,
      "is_attacker": false
    },
    "178": {
      "accuracy": 0.8966999650001526,
      "test_loss": 0.3596823513507843,
      "precision": 1.0,
      "recall": 0.0,
      "f1_score": 0.0,
      "update_norm": 0.05185744911432266,
      "is_attacker": false
    },
    "179": {
      "accuracy": 0.8946999907493591,
      "test_loss": 0.3637814223766327,
      "precision": 1.0,
      "recall": 0.0,
      "f1_score": 0.0,
      "update_norm": 0.04832780733704567,
      "is_attacker": false
    },
    "180": {
      "accuracy": 0.8966999650001526,
      "test_loss": 0.36233460903167725,
      "precision": 1.0,
      "recall": 0.0,
      "f1_score": 0.0,
      "update_norm": 0.049319054931402206,
      "is_attacker": false
    },
    "181": {
      "accuracy": 0.8950999975204468,
      "test_loss": 0.36238154768943787,
      "precision": 1.0,
      "recall": 0.0,
      "f1_score": 0.0,
      "update_norm": 0.04709823802113533,
      "is_attacker": false
    },
    "182": {
      "accuracy": 0.8913999795913696,
      "test_loss": 0.3645666539669037,
      "precision": 1.0,
      "recall": 0.0,
      "f1_score": 0.0,
      "update_norm": 0.04800659790635109,
      "is_attacker": false
    },
    "183": {
      "accuracy": 0.8968999981880188,
      "test_loss": 0.3613738715648651,
      "precision": 1.0,
      "recall": 0.0,
      "f1_score": 0.0,
      "update_norm": 0.04699740931391716,
      "is_attacker": false
    },
    "184": {
      "accuracy": 0.8922999501228333,
      "test_loss": 0.3671802580356598,
      "precision": 1.0,
      "recall": 0.0,
      "f1_score": 0.0,
      "update_norm": 0.050832100212574005,
      "is_attacker": false
    },
    "185": {
      "accuracy": 0.8915999531745911,
      "test_loss": 0.36943405866622925,
      "precision": 1.0,
      "recall": 0.0,
      "f1_score": 0.0,
      "update_norm": 0.046952541917562485,
      "is_attacker": false
    },
    "186": {
      "accuracy": 0.8939999938011169,
      "test_loss": 0.36696508526802063,
      "precision": 1.0,
      "recall": 0.0,
      "f1_score": 0.0,
      "update_norm": 0.049392540007829666,
      "is_attacker": false
    },
    "187": {
      "accuracy": 0.8944999575614929,
      "test_loss": 0.3677211105823517,
      "precision": 1.0,
      "recall": 0.0,
      "f1_score": 0.0,
      "update_norm": 0.050938550382852554,
      "is_attacker": false
    },
    "188": {
      "accuracy": 0.894599974155426,
      "test_loss": 0.35913583636283875,
      "precision": 1.0,
      "recall": 0.0,
      "f1_score": 0.0,
      "update_norm": 0.04757775738835335,
      "is_attacker": false
    },
    "189": {
      "accuracy": 0.8948999643325806,
      "test_loss": 0.35994651913642883,
      "precision": 1.0,
      "recall": 0.0,
      "f1_score": 0.0,
      "update_norm": 0.04800679534673691,
      "is_attacker": false
    },
    "190": {
      "accuracy": 0.8914999961853027,
      "test_loss": 0.3592258095741272,
      "precision": 1.0,
      "recall": 0.0,
      "f1_score": 0.0,
      "update_norm": 0.046602021902799606,
      "is_attacker": false
    },
    "191": {
      "accuracy": 0.9004999995231628,
      "test_loss": 0.35025832056999207,
      "precision": 1.0,
      "recall": 0.0,
      "f1_score": 0.0,
      "update_norm": 0.05408354103565216,
      "is_attacker": false
    },
    "192": {
      "accuracy": 0.8969999551773071,
      "test_loss": 0.3600808084011078,
      "precision": 1.0,
      "recall": 0.0,
      "f1_score": 0.0,
      "update_norm": 0.04781254380941391,
      "is_attacker": false
    },
    "193": {
      "accuracy": 0.8959999680519104,
      "test_loss": 0.3553551137447357,
      "precision": 1.0,
      "recall": 0.0,
      "f1_score": 0.0,
      "update_norm": 0.04752976447343826,
      "is_attacker": false
    },
    "194": {
      "accuracy": 0.8956999778747559,
      "test_loss": 0.3670290410518646,
      "precision": 1.0,
      "recall": 0.0,
      "f1_score": 0.0,
      "update_norm": 0.04822908714413643,
      "is_attacker": false
    },
    "195": {
      "accuracy": 0.898099958896637,
      "test_loss": 0.3621293008327484,
      "precision": 1.0,
      "recall": 0.0,
      "f1_score": 0.0,
      "update_norm": 0.04942868649959564,
      "is_attacker": false
    },
    "196": {
      "accuracy": 0.8898999691009521,
      "test_loss": 0.36861029267311096,
      "precision": 1.0,
      "recall": 0.0,
      "f1_score": 0.0,
      "update_norm": 0.04654303938150406,
      "is_attacker": false
    },
    "197": {
      "accuracy": 0.8970999717712402,
      "test_loss": 0.35589277744293213,
      "precision": 1.0,
      "recall": 0.0,
      "f1_score": 0.0,
      "update_norm": 0.04930833354592323,
      "is_attacker": false
    },
    "198": {
      "accuracy": 0.8965999484062195,
      "test_loss": 0.35692712664604187,
      "precision": 1.0,
      "recall": 0.0,
      "f1_score": 0.0,
      "update_norm": 0.05025782808661461,
      "is_attacker": false
    },
    "199": {
      "accuracy": 0.8962000012397766,
      "test_loss": 0.3615519404411316,
      "precision": 1.0,
      "recall": 0.0,
      "f1_score": 0.0,
      "update_norm": 0.047889143228530884,
      "is_attacker": false
    },
    "200": {
      "accuracy": 0.8962000012397766,
      "test_loss": 0.36626091599464417,
      "precision": 1.0,
      "recall": 0.0,
      "f1_score": 0.0,
      "update_norm": 0.050484903156757355,
      "is_attacker": false
    },
    "201": {
      "accuracy": 0.8973000049591064,
      "test_loss": 0.3533634543418884,
      "precision": 1.0,
      "recall": 0.0,
      "f1_score": 0.0,
      "update_norm": 0.0481921061873436,
      "is_attacker": false
    },
    "202": {
      "accuracy": 0.8899999856948853,
      "test_loss": 0.36965876817703247,
      "precision": 1.0,
      "recall": 0.0,
      "f1_score": 0.0,
      "update_norm": 0.04700988903641701,
      "is_attacker": false
    },
    "203": {
      "accuracy": 0.8962000012397766,
      "test_loss": 0.3531430959701538,
      "precision": 1.0,
      "recall": 0.0,
      "f1_score": 0.0,
      "update_norm": 0.05211453512310982,
      "is_attacker": false
    },
    "204": {
      "accuracy": 0.8924999833106995,
      "test_loss": 0.3618408739566803,
      "precision": 1.0,
      "recall": 0.0,
      "f1_score": 0.0,
      "update_norm": 0.048184070736169815,
      "is_attacker": false
    },
    "205": {
      "accuracy": 0.8955999612808228,
      "test_loss": 0.3582746386528015,
      "precision": 1.0,
      "recall": 0.0,
      "f1_score": 0.0,
      "update_norm": 0.05257541686296463,
      "is_attacker": false
    },
    "206": {
      "accuracy": 0.897599995136261,
      "test_loss": 0.3611662983894348,
      "precision": 1.0,
      "recall": 0.0,
      "f1_score": 0.0,
      "update_norm": 0.049869850277900696,
      "is_attacker": false
    },
    "207": {
      "accuracy": 0.8959999680519104,
      "test_loss": 0.35681504011154175,
      "precision": 1.0,
      "recall": 0.0,
      "f1_score": 0.0,
      "update_norm": 0.05023415759205818,
      "is_attacker": false
    },
    "208": {
      "accuracy": 0.8944000005722046,
      "test_loss": 0.36994969844818115,
      "precision": 1.0,
      "recall": 0.0,
      "f1_score": 0.0,
      "update_norm": 0.04855681210756302,
      "is_attacker": false
    },
    "209": {
      "accuracy": 0.8940999507904053,
      "test_loss": 0.36380425095558167,
      "precision": 1.0,
      "recall": 0.0,
      "f1_score": 0.0,
      "update_norm": 0.048171840608119965,
      "is_attacker": false
    },
    "210": {
      "accuracy": 0.8930999636650085,
      "test_loss": 0.36196091771125793,
      "precision": 1.0,
      "recall": 0.0,
      "f1_score": 0.0,
      "update_norm": 0.05200202390551567,
      "is_attacker": false
    },
    "211": {
      "accuracy": 0.8956999778747559,
      "test_loss": 0.3625508248806,
      "precision": 1.0,
      "recall": 0.0,
      "f1_score": 0.0,
      "update_norm": 0.04993235319852829,
      "is_attacker": false
    },
    "212": {
      "accuracy": 0.8962999582290649,
      "test_loss": 0.3590248227119446,
      "precision": 1.0,
      "recall": 0.0,
      "f1_score": 0.0,
      "update_norm": 0.049151431769132614,
      "is_attacker": false
    },
    "213": {
      "accuracy": 0.8960999846458435,
      "test_loss": 0.3622616231441498,
      "precision": 1.0,
      "recall": 0.0,
      "f1_score": 0.0,
      "update_norm": 0.047527797520160675,
      "is_attacker": false
    },
    "214": {
      "accuracy": 0.8919999599456787,
      "test_loss": 0.3640264868736267,
      "precision": 1.0,
      "recall": 0.0,
      "f1_score": 0.0,
      "update_norm": 0.05104014277458191,
      "is_attacker": false
    },
    "215": {
      "accuracy": 0.8982999920845032,
      "test_loss": 0.36176857352256775,
      "precision": 1.0,
      "recall": 0.0,
      "f1_score": 0.0,
      "update_norm": 0.05066981539130211,
      "is_attacker": false
    },
    "216": {
      "accuracy": 0.8955000042915344,
      "test_loss": 0.3594629168510437,
      "precision": 1.0,
      "recall": 0.0,
      "f1_score": 0.0,
      "update_norm": 0.0500563383102417,
      "is_attacker": false
    },
    "217": {
      "accuracy": 0.8937999606132507,
      "test_loss": 0.36663109064102173,
      "precision": 1.0,
      "recall": 0.0,
      "f1_score": 0.0,
      "update_norm": 0.04963458329439163,
      "is_attacker": false
    },
    "218": {
      "accuracy": 0.8903999924659729,
      "test_loss": 0.3760346472263336,
      "precision": 1.0,
      "recall": 0.0,
      "f1_score": 0.0,
      "update_norm": 0.04793095961213112,
      "is_attacker": false
    },
    "219": {
      "accuracy": 0.8960999846458435,
      "test_loss": 0.35543403029441833,
      "precision": 1.0,
      "recall": 0.0,
      "f1_score": 0.0,
      "update_norm": 0.049647752195596695,
      "is_attacker": false
    },
    "220": {
      "accuracy": 0.8969999551773071,
      "test_loss": 0.36591455340385437,
      "precision": 1.0,
      "recall": 0.0,
      "f1_score": 0.0,
      "update_norm": 0.0521354041993618,
      "is_attacker": false
    },
    "221": {
      "accuracy": 0.8949999809265137,
      "test_loss": 0.3597550392150879,
      "precision": 1.0,
      "recall": 0.0,
      "f1_score": 0.0,
      "update_norm": 0.04810689762234688,
      "is_attacker": false
    },
    "222": {
      "accuracy": 0.8971999883651733,
      "test_loss": 0.35431936383247375,
      "precision": 1.0,
      "recall": 0.0,
      "f1_score": 0.0,
      "update_norm": 0.049186959862709045,
      "is_attacker": false
    },
    "223": {
      "accuracy": 0.8955999612808228,
      "test_loss": 0.3628125786781311,
      "precision": 1.0,
      "recall": 0.0,
      "f1_score": 0.0,
      "update_norm": 0.047749269753694534,
      "is_attacker": false
    },
    "224": {
      "accuracy": 0.8964999914169312,
      "test_loss": 0.3570983409881592,
      "precision": 1.0,
      "recall": 0.0,
      "f1_score": 0.0,
      "update_norm": 0.053040679544210434,
      "is_attacker": false
    },
    "225": {
      "accuracy": 0.8948999643325806,
      "test_loss": 0.36452654004096985,
      "precision": 1.0,
      "recall": 0.0,
      "f1_score": 0.0,
      "update_norm": 0.04848279058933258,
      "is_attacker": false
    },
    "226": {
      "accuracy": 0.8973999619483948,
      "test_loss": 0.3562743365764618,
      "precision": 1.0,
      "recall": 0.0,
      "f1_score": 0.0,
      "update_norm": 0.048799894750118256,
      "is_attacker": false
    },
    "227": {
      "accuracy": 0.8955000042915344,
      "test_loss": 0.36611562967300415,
      "precision": 1.0,
      "recall": 0.0,
      "f1_score": 0.0,
      "update_norm": 0.048515524715185165,
      "is_attacker": false
    },
    "228": {
      "accuracy": 0.8981999754905701,
      "test_loss": 0.35368242859840393,
      "precision": 1.0,
      "recall": 0.0,
      "f1_score": 0.0,
      "update_norm": 0.05249899625778198,
      "is_attacker": false
    },
    "229": {
      "accuracy": 0.8919999599456787,
      "test_loss": 0.36321914196014404,
      "precision": 1.0,
      "recall": 0.0,
      "f1_score": 0.0,
      "update_norm": 0.05271753668785095,
      "is_attacker": false
    },
    "230": {
      "accuracy": 0.897599995136261,
      "test_loss": 0.3621947765350342,
      "precision": 1.0,
      "recall": 0.0,
      "f1_score": 0.0,
      "update_norm": 0.048106539994478226,
      "is_attacker": false
    },
    "231": {
      "accuracy": 0.8914999961853027,
      "test_loss": 0.36756569147109985,
      "precision": 1.0,
      "recall": 0.0,
      "f1_score": 0.0,
      "update_norm": 0.048873625695705414,
      "is_attacker": false
    },
    "232": {
      "accuracy": 0.8921999931335449,
      "test_loss": 0.3632770776748657,
      "precision": 1.0,
      "recall": 0.0,
      "f1_score": 0.0,
      "update_norm": 0.04819182679057121,
      "is_attacker": false
    },
    "233": {
      "accuracy": 0.8920999765396118,
      "test_loss": 0.367377370595932,
      "precision": 1.0,
      "recall": 0.0,
      "f1_score": 0.0,
      "update_norm": 0.04824736341834068,
      "is_attacker": false
    },
    "234": {
      "accuracy": 0.8965999484062195,
      "test_loss": 0.35558679699897766,
      "precision": 1.0,
      "recall": 0.0,
      "f1_score": 0.0,
      "update_norm": 0.049172572791576385,
      "is_attacker": false
    },
    "235": {
      "accuracy": 0.8970999717712402,
      "test_loss": 0.3609129786491394,
      "precision": 1.0,
      "recall": 0.0,
      "f1_score": 0.0,
      "update_norm": 0.048612080514431,
      "is_attacker": false
    },
    "236": {
      "accuracy": 0.8995999693870544,
      "test_loss": 0.35109004378318787,
      "precision": 1.0,
      "recall": 0.0,
      "f1_score": 0.0,
      "update_norm": 0.04745291918516159,
      "is_attacker": false
    },
    "237": {
      "accuracy": 0.8978999853134155,
      "test_loss": 0.3600718080997467,
      "precision": 1.0,
      "recall": 0.0,
      "f1_score": 0.0,
      "update_norm": 0.05063294246792793,
      "is_attacker": false
    },
    "238": {
      "accuracy": 0.8949999809265137,
      "test_loss": 0.35920611023902893,
      "precision": 1.0,
      "recall": 0.0,
      "f1_score": 0.0,
      "update_norm": 0.04845463111996651,
      "is_attacker": false
    },
    "239": {
      "accuracy": 0.8967999815940857,
      "test_loss": 0.3536459505558014,
      "precision": 1.0,
      "recall": 0.0,
      "f1_score": 0.0,
      "update_norm": 0.0489591620862484,
      "is_attacker": false
    },
    "240": {
      "accuracy": 0.8930000066757202,
      "test_loss": 0.36656445264816284,
      "precision": 1.0,
      "recall": 0.0,
      "f1_score": 0.0,
      "update_norm": 0.050123054534196854,
      "is_attacker": false
    },
    "241": {
      "accuracy": 0.8941999673843384,
      "test_loss": 0.3614591062068939,
      "precision": 1.0,
      "recall": 0.0,
      "f1_score": 0.0,
      "update_norm": 0.047961071133613586,
      "is_attacker": false
    },
    "242": {
      "accuracy": 0.8958999514579773,
      "test_loss": 0.3627223074436188,
      "precision": 1.0,
      "recall": 0.0,
      "f1_score": 0.0,
      "update_norm": 0.04784326255321503,
      "is_attacker": false
    },
    "243": {
      "accuracy": 0.8930000066757202,
      "test_loss": 0.3698618412017822,
      "precision": 1.0,
      "recall": 0.0,
      "f1_score": 0.0,
      "update_norm": 0.05232350155711174,
      "is_attacker": false
    },
    "244": {
      "accuracy": 0.8937000036239624,
      "test_loss": 0.3708421289920807,
      "precision": 1.0,
      "recall": 0.0,
      "f1_score": 0.0,
      "update_norm": 0.04690919816493988,
      "is_attacker": false
    },
    "245": {
      "accuracy": 0.8930000066757202,
      "test_loss": 0.3667442798614502,
      "precision": 1.0,
      "recall": 0.0,
      "f1_score": 0.0,
      "update_norm": 0.04656610265374184,
      "is_attacker": false
    },
    "246": {
      "accuracy": 0.8906999826431274,
      "test_loss": 0.36763525009155273,
      "precision": 1.0,
      "recall": 0.0,
      "f1_score": 0.0,
      "update_norm": 0.0481843426823616,
      "is_attacker": false
    },
    "247": {
      "accuracy": 0.8946999907493591,
      "test_loss": 0.36388787627220154,
      "precision": 1.0,
      "recall": 0.0,
      "f1_score": 0.0,
      "update_norm": 0.05001487210392952,
      "is_attacker": false
    },
    "248": {
      "accuracy": 0.8938999772071838,
      "test_loss": 0.36591026186943054,
      "precision": 1.0,
      "recall": 0.0,
      "f1_score": 0.0,
      "update_norm": 0.04810862988233566,
      "is_attacker": false
    },
    "249": {
      "accuracy": 0.901699960231781,
      "test_loss": 0.3516404330730438,
      "precision": 1.0,
      "recall": 0.0,
      "f1_score": 0.0,
      "update_norm": 0.047900982201099396,
      "is_attacker": false
    },
    "250": {
      "accuracy": 0.8973000049591064,
      "test_loss": 0.36451154947280884,
      "precision": 1.0,
      "recall": 0.0,
      "f1_score": 0.0,
      "update_norm": 0.048531852662563324,
      "is_attacker": false
    },
    "251": {
      "accuracy": 0.8947999477386475,
      "test_loss": 0.3621114194393158,
      "precision": 1.0,
      "recall": 0.0,
      "f1_score": 0.0,
      "update_norm": 0.04749054089188576,
      "is_attacker": false
    },
    "252": {
      "accuracy": 0.894599974155426,
      "test_loss": 0.36739519238471985,
      "precision": 1.0,
      "recall": 0.0,
      "f1_score": 0.0,
      "update_norm": 0.04912149906158447,
      "is_attacker": false
    },
    "253": {
      "accuracy": 0.8973000049591064,
      "test_loss": 0.36468350887298584,
      "precision": 1.0,
      "recall": 0.0,
      "f1_score": 0.0,
      "update_norm": 0.04773540049791336,
      "is_attacker": false
    },
    "254": {
      "accuracy": 0.8988999724388123,
      "test_loss": 0.3543541133403778,
      "precision": 1.0,
      "recall": 0.0,
      "f1_score": 0.0,
      "update_norm": 0.04882146418094635,
      "is_attacker": false
    },
    "255": {
      "accuracy": 0.8931999802589417,
      "test_loss": 0.3624904751777649,
      "precision": 1.0,
      "recall": 0.0,
      "f1_score": 0.0,
      "update_norm": 0.04874701797962189,
      "is_attacker": false
    },
    "256": {
      "accuracy": 0.8953999876976013,
      "test_loss": 0.3655282258987427,
      "precision": 1.0,
      "recall": 0.0,
      "f1_score": 0.0,
      "update_norm": 0.04811719432473183,
      "is_attacker": false
    },
    "257": {
      "accuracy": 0.8962999582290649,
      "test_loss": 0.35782068967819214,
      "precision": 1.0,
      "recall": 0.0,
      "f1_score": 0.0,
      "update_norm": 0.05067028850317001,
      "is_attacker": false
    },
    "258": {
      "accuracy": 0.8921999931335449,
      "test_loss": 0.3636806905269623,
      "precision": 1.0,
      "recall": 0.0,
      "f1_score": 0.0,
      "update_norm": 0.049688808619976044,
      "is_attacker": false
    },
    "259": {
      "accuracy": 0.8934999704360962,
      "test_loss": 0.3619272708892822,
      "precision": 1.0,
      "recall": 0.0,
      "f1_score": 0.0,
      "update_norm": 0.04851074144244194,
      "is_attacker": false
    },
    "260": {
      "accuracy": 0.8968999981880188,
      "test_loss": 0.3571091592311859,
      "precision": 1.0,
      "recall": 0.0,
      "f1_score": 0.0,
      "update_norm": 0.04851185902953148,
      "is_attacker": false
    },
    "261": {
      "accuracy": 0.8931999802589417,
      "test_loss": 0.3649015426635742,
      "precision": 1.0,
      "recall": 0.0,
      "f1_score": 0.0,
      "update_norm": 0.047378119081258774,
      "is_attacker": false
    },
    "262": {
      "accuracy": 0.8939999938011169,
      "test_loss": 0.36624011397361755,
      "precision": 1.0,
      "recall": 0.0,
      "f1_score": 0.0,
      "update_norm": 0.046024758368730545,
      "is_attacker": false
    },
    "263": {
      "accuracy": 0.8984999656677246,
      "test_loss": 0.35846763849258423,
      "precision": 1.0,
      "recall": 0.0,
      "f1_score": 0.0,
      "update_norm": 0.04943491518497467,
      "is_attacker": false
    },
    "264": {
      "accuracy": 0.8948999643325806,
      "test_loss": 0.36447885632514954,
      "precision": 1.0,
      "recall": 0.0,
      "f1_score": 0.0,
      "update_norm": 0.049637824296951294,
      "is_attacker": false
    },
    "265": {
      "accuracy": 0.8919999599456787,
      "test_loss": 0.3624749183654785,
      "precision": 1.0,
      "recall": 0.0,
      "f1_score": 0.0,
      "update_norm": 0.04642430692911148,
      "is_attacker": false
    },
    "266": {
      "accuracy": 0.8935999870300293,
      "test_loss": 0.36366021633148193,
      "precision": 1.0,
      "recall": 0.0,
      "f1_score": 0.0,
      "update_norm": 0.04673878848552704,
      "is_attacker": false
    },
    "267": {
      "accuracy": 0.8955999612808228,
      "test_loss": 0.3624938726425171,
      "precision": 1.0,
      "recall": 0.0,
      "f1_score": 0.0,
      "update_norm": 0.047999631613492966,
      "is_attacker": false
    },
    "268": {
      "accuracy": 0.8932999968528748,
      "test_loss": 0.37514570355415344,
      "precision": 1.0,
      "recall": 0.0,
      "f1_score": 0.0,
      "update_norm": 0.0481308177113533,
      "is_attacker": false
    },
    "269": {
      "accuracy": 0.8970999717712402,
      "test_loss": 0.35757556557655334,
      "precision": 1.0,
      "recall": 0.0,
      "f1_score": 0.0,
      "update_norm": 0.049084290862083435,
      "is_attacker": false
    },
    "270": {
      "accuracy": 0.8932999968528748,
      "test_loss": 0.3664170205593109,
      "precision": 1.0,
      "recall": 0.0,
      "f1_score": 0.0,
      "update_norm": 0.05140836536884308,
      "is_attacker": false
    },
    "271": {
      "accuracy": 0.8946999907493591,
      "test_loss": 0.35641157627105713,
      "precision": 1.0,
      "recall": 0.0,
      "f1_score": 0.0,
      "update_norm": 0.04721272364258766,
      "is_attacker": false
    },
    "272": {
      "accuracy": 0.8931999802589417,
      "test_loss": 0.3611798584461212,
      "precision": 1.0,
      "recall": 0.0,
      "f1_score": 0.0,
      "update_norm": 0.04945460334420204,
      "is_attacker": false
    },
    "273": {
      "accuracy": 0.8946999907493591,
      "test_loss": 0.3634122908115387,
      "precision": 1.0,
      "recall": 0.0,
      "f1_score": 0.0,
      "update_norm": 0.04832591861486435,
      "is_attacker": false
    },
    "274": {
      "accuracy": 0.8973999619483948,
      "test_loss": 0.35822954773902893,
      "precision": 1.0,
      "recall": 0.0,
      "f1_score": 0.0,
      "update_norm": 0.05064971745014191,
      "is_attacker": false
    },
    "275": {
      "accuracy": 0.8952999711036682,
      "test_loss": 0.35941293835639954,
      "precision": 1.0,
      "recall": 0.0,
      "f1_score": 0.0,
      "update_norm": 0.04737690091133118,
      "is_attacker": false
    },
    "276": {
      "accuracy": 0.899399995803833,
      "test_loss": 0.3555702865123749,
      "precision": 1.0,
      "recall": 0.0,
      "f1_score": 0.0,
      "update_norm": 0.04822617769241333,
      "is_attacker": false
    },
    "277": {
      "accuracy": 0.8942999839782715,
      "test_loss": 0.3637494146823883,
      "precision": 1.0,
      "recall": 0.0,
      "f1_score": 0.0,
      "update_norm": 0.04938933625817299,
      "is_attacker": false
    },
    "278": {
      "accuracy": 0.8962000012397766,
      "test_loss": 0.3604048490524292,
      "precision": 1.0,
      "recall": 0.0,
      "f1_score": 0.0,
      "update_norm": 0.04732003062963486,
      "is_attacker": false
    },
    "279": {
      "accuracy": 0.8952999711036682,
      "test_loss": 0.3634515404701233,
      "precision": 1.0,
      "recall": 0.0,
      "f1_score": 0.0,
      "update_norm": 0.04761195182800293,
      "is_attacker": false
    },
    "280": {
      "accuracy": 0.8937000036239624,
      "test_loss": 0.3567260205745697,
      "precision": 1.0,
      "recall": 0.0,
      "f1_score": 0.0,
      "update_norm": 0.049795202910900116,
      "is_attacker": false
    },
    "281": {
      "accuracy": 0.8966999650001526,
      "test_loss": 0.35469356179237366,
      "precision": 1.0,
      "recall": 0.0,
      "f1_score": 0.0,
      "update_norm": 0.04687199369072914,
      "is_attacker": false
    },
    "282": {
      "accuracy": 0.8978999853134155,
      "test_loss": 0.3553066551685333,
      "precision": 1.0,
      "recall": 0.0,
      "f1_score": 0.0,
      "update_norm": 0.04662046208977699,
      "is_attacker": false
    },
    "283": {
      "accuracy": 0.8930000066757202,
      "test_loss": 0.3669470250606537,
      "precision": 1.0,
      "recall": 0.0,
      "f1_score": 0.0,
      "update_norm": 0.04723723605275154,
      "is_attacker": false
    },
    "284": {
      "accuracy": 0.8994999527931213,
      "test_loss": 0.36100873351097107,
      "precision": 1.0,
      "recall": 0.0,
      "f1_score": 0.0,
      "update_norm": 0.04990959167480469,
      "is_attacker": false
    },
    "285": {
      "accuracy": 0.8985999822616577,
      "test_loss": 0.3553507626056671,
      "precision": 1.0,
      "recall": 0.0,
      "f1_score": 0.0,
      "update_norm": 0.04884428158402443,
      "is_attacker": false
    },
    "286": {
      "accuracy": 0.8934999704360962,
      "test_loss": 0.37370315194129944,
      "precision": 1.0,
      "recall": 0.0,
      "f1_score": 0.0,
      "update_norm": 0.04984118416905403,
      "is_attacker": false
    },
    "287": {
      "accuracy": 0.8931999802589417,
      "test_loss": 0.36539900302886963,
      "precision": 1.0,
      "recall": 0.0,
      "f1_score": 0.0,
      "update_norm": 0.047147586941719055,
      "is_attacker": false
    },
    "288": {
      "accuracy": 0.8939999938011169,
      "test_loss": 0.3568899929523468,
      "precision": 1.0,
      "recall": 0.0,
      "f1_score": 0.0,
      "update_norm": 0.04864376410841942,
      "is_attacker": false
    },
    "289": {
      "accuracy": 0.8910999894142151,
      "test_loss": 0.36794888973236084,
      "precision": 1.0,
      "recall": 0.0,
      "f1_score": 0.0,
      "update_norm": 0.04748544096946716,
      "is_attacker": false
    },
    "290": {
      "accuracy": 0.896399974822998,
      "test_loss": 0.3637605905532837,
      "precision": 1.0,
      "recall": 0.0,
      "f1_score": 0.0,
      "update_norm": 0.04836773872375488,
      "is_attacker": false
    },
    "291": {
      "accuracy": 0.8966999650001526,
      "test_loss": 0.3569771349430084,
      "precision": 1.0,
      "recall": 0.0,
      "f1_score": 0.0,
      "update_norm": 0.050542060285806656,
      "is_attacker": false
    },
    "292": {
      "accuracy": 0.8932999968528748,
      "test_loss": 0.3628133237361908,
      "precision": 1.0,
      "recall": 0.0,
      "f1_score": 0.0,
      "update_norm": 0.04698667302727699,
      "is_attacker": false
    },
    "293": {
      "accuracy": 0.8984999656677246,
      "test_loss": 0.35646387934684753,
      "precision": 1.0,
      "recall": 0.0,
      "f1_score": 0.0,
      "update_norm": 0.049989525228738785,
      "is_attacker": false
    },
    "294": {
      "accuracy": 0.8960999846458435,
      "test_loss": 0.3591485023498535,
      "precision": 1.0,
      "recall": 0.0,
      "f1_score": 0.0,
      "update_norm": 0.04928770661354065,
      "is_attacker": false
    },
    "295": {
      "accuracy": 0.8944999575614929,
      "test_loss": 0.3617613613605499,
      "precision": 1.0,
      "recall": 0.0,
      "f1_score": 0.0,
      "update_norm": 0.05020879954099655,
      "is_attacker": false
    },
    "296": {
      "accuracy": 0.8971999883651733,
      "test_loss": 0.3543529808521271,
      "precision": 1.0,
      "recall": 0.0,
      "f1_score": 0.0,
      "update_norm": 0.048005566000938416,
      "is_attacker": false
    },
    "297": {
      "accuracy": 0.8950999975204468,
      "test_loss": 0.3577759563922882,
      "precision": 1.0,
      "recall": 0.0,
      "f1_score": 0.0,
      "update_norm": 0.047776900231838226,
      "is_attacker": false
    },
    "298": {
      "accuracy": 0.8932999968528748,
      "test_loss": 0.36330294609069824,
      "precision": 1.0,
      "recall": 0.0,
      "f1_score": 0.0,
      "update_norm": 0.04840287193655968,
      "is_attacker": false
    },
    "299": {
      "accuracy": 0.8977999687194824,
      "test_loss": 0.3564301133155823,
      "precision": 1.0,
      "recall": 0.0,
      "f1_score": 0.0,
      "update_norm": 0.04848289489746094,
      "is_attacker": false
    }
  }
}